[
  {
    "English": null,
    "ids": [
      "map_beyond_portal_search_radius_+%"
    ],
    "trade_stats": null,
    "hidden": null,
    "French": null,
    "German": null,
    "Japanese": null,
    "Korean": null,
    "Portuguese": null,
    "Russian": [
      {
        "condition": [
          {
            "min": null,
            "max": null,
            "negated": null
          }
        ],
        "format": [
          "#"
        ],
        "index_handlers": [
          []
        ],
        "string": "{0}% увеличение радиуса слияния [CoalescedCorruption|Сросшейся порчи] на ваших картах",
        "reminder_text": null,
        "is_markup": null
      }
    ],
    "Spanish": null,
    "Thai": null,
    "Traditional_Chinese": null
  },
  {
    "English": null,
    "ids": [
      "map_breach_fruit_amulet_chance_+%"
    ],
    "trade_stats": null,
    "hidden": null,
    "French": null,
    "German": null,
    "Japanese": null,
    "Korean": null,
    "Portuguese": null,
    "Russian": [
      {
        "condition": [
          {
            "min": 1,
            "max": null,
            "negated": null
          }
        ],
        "format": [
          "#"
        ],
        "index_handlers": [
          []
        ],
        "string": "{0}% увеличение шанса нахождения [BreachFruitAmulet|украшенных даров утробы]",
        "reminder_text": null,
        "is_markup": null
      },
      {
        "condition": [
          {
            "min": null,
            "max": -1,
            "negated": null
          }
        ],
        "format": [
          "#"
        ],
        "index_handlers": [
          [
            "negate"
          ]
        ],
        "string": "{0}% уменьшение шанса нахождения [BreachFruitAmulet|украшенных даров утробы]",
        "reminder_text": null,
        "is_markup": null
      }
    ],
    "Spanish": null,
    "Thai": null,
    "Traditional_Chinese": null
  },
  {
    "English": null,
    "ids": [
      "map_breach_fruit_belt_chance_+%"
    ],
    "trade_stats": null,
    "hidden": null,
    "French": null,
    "German": null,
    "Japanese": null,
    "Korean": null,
    "Portuguese": null,
    "Russian": [
      {
        "condition": [
          {
            "min": 1,
            "max": null,
            "negated": null
          }
        ],
        "format": [
          "#"
        ],
        "index_handlers": [
          []
        ],
        "string": "{0}% увеличение шанса нахождения [BreachFruitAmulet|обмотанных даров утробы]",
        "reminder_text": null,
        "is_markup": null
      },
      {
        "condition": [
          {
            "min": null,
            "max": -1,
            "negated": null
          }
        ],
        "format": [
          "#"
        ],
        "index_handlers": [
          [
            "negate"
          ]
        ],
        "string": "{0}% уменьшение шанса нахождения [BreachFruitAmulet|обмотанных даров утробы]",
        "reminder_text": null,
        "is_markup": null
      }
    ],
    "Spanish": null,
    "Thai": null,
    "Traditional_Chinese": null
  },
  {
    "English": null,
    "ids": [
      "map_breach_fruit_currency_chance_+%"
    ],
    "trade_stats": null,
    "hidden": null,
    "French": null,
    "German": null,
    "Japanese": null,
    "Korean": null,
    "Portuguese": null,
    "Russian": [
      {
        "condition": [
          {
            "min": 1,
            "max": null,
            "negated": null
          }
        ],
        "format": [
          "#"
        ],
        "index_handlers": [
          []
        ],
        "string": "{0}% увеличение шанса нахождения [BreachFruitAmulet|обильных даров утробы]",
        "reminder_text": null,
        "is_markup": null
      },
      {
        "condition": [
          {
            "min": null,
            "max": -1,
            "negated": null
          }
        ],
        "format": [
          "#"
        ],
        "index_handlers": [
          [
            "negate"
          ]
        ],
        "string": "{0}% уменьшение шанса нахождения [BreachFruitAmulet|обильных даров утробы]",
        "reminder_text": null,
        "is_markup": null
      }
    ],
    "Spanish": null,
    "Thai": null,
    "Traditional_Chinese": null
  },
  {
    "English": null,
    "ids": [
      "map_breach_fruit_ring_chance_+%"
    ],
    "trade_stats": null,
    "hidden": null,
    "French": null,
    "German": null,
    "Japanese": null,
    "Korean": null,
    "Portuguese": null,
    "Russian": [
      {
        "condition": [
          {
            "min": 1,
            "max": null,
            "negated": null
          }
        ],
        "format": [
          "#"
        ],
        "index_handlers": [
          []
        ],
        "string": "{0}% увеличение шанса нахождения [BreachFruitAmulet|опечатанных даров утробы]",
        "reminder_text": null,
        "is_markup": null
      },
      {
        "condition": [
          {
            "min": null,
            "max": -1,
            "negated": null
          }
        ],
        "format": [
          "#"
        ],
        "index_handlers": [
          [
            "negate"
          ]
        ],
        "string": "{0}% уменьшение шанса нахождения [BreachFruitAmulet|опечатанных даров утробы]",
        "reminder_text": null,
        "is_markup": null
      }
    ],
    "Spanish": null,
    "Thai": null,
    "Traditional_Chinese": null
  },
  {
    "English": null,
    "ids": [
      "map_breach_hive_number_of_skills_+%"
    ],
    "trade_stats": null,
    "hidden": null,
    "French": null,
    "German": null,
    "Japanese": null,
    "Korean": null,
    "Portuguese": null,
    "Russian": [
      {
        "condition": [
          {
            "min": 1,
            "max": null,
            "negated": null
          }
        ],
        "format": [
          "#"
        ],
        "index_handlers": [
          []
        ],
        "string": "{0}% increased number of skills created by Ailith",
        "reminder_text": null,
        "is_markup": null
      },
      {
        "condition": [
          {
            "min": null,
            "max": -1,
            "negated": null
          }
        ],
        "format": [
          "#"
        ],
        "index_handlers": [
          [
            "negate"
          ]
        ],
        "string": "{0}% reduced number of skills created by Ailith",
        "reminder_text": null,
        "is_markup": null
      }
    ],
    "Spanish": null,
    "Thai": null,
    "Traditional_Chinese": null
  },
  {
    "English": null,
    "ids": [
      "map_breach_hive_skill_damage_+%"
    ],
    "trade_stats": null,
    "hidden": null,
    "French": null,
    "German": null,
    "Japanese": null,
    "Korean": null,
    "Portuguese": null,
    "Russian": [
      {
        "condition": [
          {
            "min": 1,
            "max": null,
            "negated": null
          }
        ],
        "format": [
          "#"
        ],
        "index_handlers": [
          []
        ],
        "string": "{0}% increased damage of skills created by Ailith",
        "reminder_text": null,
        "is_markup": null
      },
      {
        "condition": [
          {
            "min": null,
            "max": -1,
            "negated": null
          }
        ],
        "format": [
          "#"
        ],
        "index_handlers": [
          [
            "negate"
          ]
        ],
        "string": "{0}% reduced damage of skills created by Ailith",
        "reminder_text": null,
        "is_markup": null
      }
    ],
    "Spanish": null,
    "Thai": null,
    "Traditional_Chinese": null
  },
  {
    "English": null,
    "ids": [
      "map_breach_hiveblood_quantity_+%"
    ],
    "trade_stats": null,
    "hidden": null,
    "French": null,
    "German": null,
    "Japanese": null,
    "Korean": null,
    "Portuguese": null,
    "Russian": [
      {
        "condition": [
          {
            "min": 1,
            "max": null,
            "negated": null
          }
        ],
        "format": [
          "#"
        ],
        "index_handlers": [
          []
        ],
        "string": "{0}% увеличение количества находимой крови улья",
        "reminder_text": null,
        "is_markup": null
      },
      {
        "condition": [
          {
            "min": null,
            "max": -1,
            "negated": null
          }
        ],
        "format": [
          "#"
        ],
        "index_handlers": [
          [
            "negate"
          ]
        ],
        "string": "{0}% уменьшение количества находимой крови улья",
        "reminder_text": null,
        "is_markup": null
      }
    ],
    "Spanish": null,
    "Thai": null,
    "Traditional_Chinese": null
  },
  {
    "English": null,
    "ids": [
      "map_breach_hives_additional_waves_+"
    ],
    "trade_stats": null,
    "hidden": null,
    "French": null,
    "German": null,
    "Japanese": null,
    "Korean": null,
    "Portuguese": null,
    "Russian": [
      {
        "condition": [
          {
            "min": 1,
            "max": 1,
            "negated": null
          }
        ],
        "format": [
          "ignore"
        ],
        "index_handlers": [
          []
        ],
        "string": "1 additional wave of Hiveborn Monsters",
        "reminder_text": null,
        "is_markup": null
      },
      {
        "condition": [
          {
            "min": null,
            "max": null,
            "negated": null
          }
        ],
        "format": [
          "#"
        ],
        "index_handlers": [
          []
        ],
        "string": "{0} additional waves of Hiveborn Monsters",
        "reminder_text": null,
        "is_markup": null
      }
    ],
    "Spanish": null,
    "Thai": null,
    "Traditional_Chinese": null
  },
  {
    "English": null,
    "ids": [
      "map_breach_monster_potency_+%"
    ],
    "trade_stats": null,
    "hidden": null,
    "French": null,
    "German": null,
    "Japanese": null,
    "Korean": null,
    "Portuguese": null,
    "Russian": [
      {
        "condition": [
          {
            "min": 1,
            "max": null,
            "negated": null
          }
        ],
        "format": [
          "#"
        ],
        "index_handlers": [
          []
        ],
        "string": "{0}% increased [MonsterEffectiveness|Effectiveness] of [ContainsBreach|Breach] Monsters",
        "reminder_text": null,
        "is_markup": null
      },
      {
        "condition": [
          {
            "min": null,
            "max": -1,
            "negated": null
          }
        ],
        "format": [
          "#"
        ],
        "index_handlers": [
          [
            "negate"
          ]
        ],
        "string": "{0}% reduced [MonsterEffectiveness|Effectiveness] of [ContainsBreach|Breach] Monsters",
        "reminder_text": null,
        "is_markup": null
      }
    ],
    "Spanish": null,
    "Thai": null,
    "Traditional_Chinese": null
  },
  {
    "English": null,
    "ids": [
      "map_breach_monster_quantity_+%"
    ],
    "trade_stats": null,
    "hidden": null,
    "French": null,
    "German": null,
    "Japanese": null,
    "Korean": null,
    "Portuguese": null,
    "Russian": [
      {
        "condition": [
          {
            "min": 1,
            "max": null,
            "negated": null
          }
        ],
        "format": [
          "#"
        ],
        "index_handlers": [
          []
        ],
        "string": "{0}% увеличение кучности монстров в [ContainsBreach|Разломах]",
        "reminder_text": null,
        "is_markup": null
      },
      {
        "condition": [
          {
            "min": null,
            "max": -1,
            "negated": null
          }
        ],
        "format": [
          "#"
        ],
        "index_handlers": [
          [
            "negate"
          ]
        ],
        "string": "{0}% уменьшение кучности монстров в [ContainsBreach|Разломах]",
        "reminder_text": null,
        "is_markup": null
      }
    ],
    "Spanish": null,
    "Thai": null,
    "Traditional_Chinese": null
  },
  {
    "English": null,
    "ids": [
      "map_breach_rare_monster_potency_+%"
    ],
    "trade_stats": null,
    "hidden": null,
    "French": null,
    "German": null,
    "Japanese": null,
    "Korean": null,
    "Portuguese": null,
    "Russian": [
      {
        "condition": [
          {
            "min": 1,
            "max": null,
            "negated": null
          }
        ],
        "format": [
          "#"
        ],
        "index_handlers": [
          []
        ],
        "string": "{0}% увеличение [MonsterEffectiveness|эффективности] [Rarity|редких] монстров [ContainsBreach|Разлома]",
        "reminder_text": null,
        "is_markup": null
      },
      {
        "condition": [
          {
            "min": null,
            "max": -1,
            "negated": null
          }
        ],
        "format": [
          "#"
        ],
        "index_handlers": [
          [
            "negate"
          ]
        ],
        "string": "{0}% уменьшение [MonsterEffectiveness|эффективности] [Rarity|редких] монстров [ContainsBreach|Разлома]",
        "reminder_text": null,
        "is_markup": null
      }
    ],
    "Spanish": null,
    "Thai": null,
    "Traditional_Chinese": null
  },
  {
    "English": null,
    "ids": [
      "map_breach_wombgift_quantity_+%"
    ],
    "trade_stats": null,
    "hidden": null,
    "French": null,
    "German": null,
    "Japanese": null,
    "Korean": null,
    "Portuguese": null,
    "Russian": [
      {
        "condition": [
          {
            "min": 1,
            "max": null,
            "negated": null
          }
        ],
        "format": [
          "#"
        ],
        "index_handlers": [
          []
        ],
        "string": "{0}% увеличение количества находимых [BreachWombgift|даров утробы]",
        "reminder_text": null,
        "is_markup": null
      },
      {
        "condition": [
          {
            "min": null,
            "max": -1,
            "negated": null
          }
        ],
        "format": [
          "#"
        ],
        "index_handlers": [
          [
            "negate"
          ]
        ],
        "string": "{0}% уменьшение количества находимых [BreachWombgift|даров утробы]",
        "reminder_text": null,
        "is_markup": null
      }
    ],
    "Spanish": null,
    "Thai": null,
    "Traditional_Chinese": null
  },
  {
    "English": null,
    "ids": [
      "map_contains_corruption_strongbox"
    ],
    "trade_stats": null,
    "hidden": null,
    "French": null,
    "German": null,
    "Japanese": null,
    "Korean": null,
    "Portuguese": null,
    "Russian": [
      {
        "condition": [
          {
            "min": 1,
            "max": 1,
            "negated": null
          }
        ],
        "format": [
          "ignore"
        ],
        "index_handlers": [
          []
        ],
        "string": "В области можно встретить кусок затвердевшей порчи",
        "reminder_text": null,
        "is_markup": null
      }
    ],
    "Spanish": null,
    "Thai": null,
    "Traditional_Chinese": null
  },
  {
    "English": null,
    "ids": [
      "map_essence_monsters_chance_for_2_additional_essences_%"
    ],
    "trade_stats": null,
    "hidden": null,
    "French": null,
    "German": null,
    "Japanese": null,
    "Korean": null,
    "Portuguese": null,
    "Russian": [
      {
        "condition": [
          {
            "min": null,
            "max": null,
            "negated": null
          }
        ],
        "format": [
          "#"
        ],
        "index_handlers": [
          []
        ],
        "string": "Плененные на ваших картах монстры с {0}% шансом могут иметь 2 дополнительные [Essence|Сущности]",
        "reminder_text": null,
        "is_markup": null
      }
    ],
    "Spanish": null,
    "Thai": null,
    "Traditional_Chinese": null
  },
  {
    "English": null,
    "ids": [
      "map_level_+_display_endgame_map"
    ],
    "trade_stats": null,
    "hidden": null,
    "French": null,
    "German": null,
    "Japanese": null,
    "Korean": null,
    "Portuguese": null,
    "Russian": [
      {
        "condition": [
          {
            "min": null,
            "max": null,
            "negated": null
          }
        ],
        "format": [
          "+#"
        ],
        "index_handlers": [
          []
        ],
        "string": "{0} к уровню монстров в области",
        "reminder_text": null,
        "is_markup": null
      }
    ],
    "Spanish": null,
    "Thai": null,
    "Traditional_Chinese": null
  },
  {
    "English": null,
    "ids": [
      "map_monster_damage_+%_final_from_deadly_atlas"
    ],
    "trade_stats": null,
    "hidden": null,
    "French": null,
    "German": null,
    "Japanese": null,
    "Korean": null,
    "Portuguese": null,
    "Russian": [
      {
        "condition": [
          {
            "min": 1,
            "max": null,
            "negated": null
          }
        ],
        "format": [
          "#"
        ],
        "index_handlers": [
          []
        ],
        "string": "Монстры на ваших картах наносят на {0}% больше урона",
        "reminder_text": null,
        "is_markup": null
      },
      {
        "condition": [
          {
            "min": null,
            "max": -1,
            "negated": null
          }
        ],
        "format": [
          "#"
        ],
        "index_handlers": [
          [
            "negate"
          ]
        ],
        "string": "Монстры на ваших картах наносят на {0}% меньше урона",
        "reminder_text": null,
        "is_markup": null
      }
    ],
    "Spanish": null,
    "Thai": null,
    "Traditional_Chinese": null
  },
  {
    "English": null,
    "ids": [
      "map_monster_damage_+%_final_from_vital_atlas"
    ],
    "trade_stats": null,
    "hidden": null,
    "French": null,
    "German": null,
    "Japanese": null,
    "Korean": null,
    "Portuguese": null,
    "Russian": [
      {
        "condition": [
          {
            "min": 1,
            "max": null,
            "negated": null
          }
        ],
        "format": [
          "#"
        ],
        "index_handlers": [
          []
        ],
        "string": "Монстры на ваших картах наносят на {0}% больше урона",
        "reminder_text": null,
        "is_markup": null
      },
      {
        "condition": [
          {
            "min": null,
            "max": -1,
            "negated": null
          }
        ],
        "format": [
          "#"
        ],
        "index_handlers": [
          [
            "negate"
          ]
        ],
        "string": "Монстры на ваших картах наносят на {0}% меньше урона",
        "reminder_text": null,
        "is_markup": null
      }
    ],
    "Spanish": null,
    "Thai": null,
    "Traditional_Chinese": null
  },
  {
    "English": null,
    "ids": [
      "map_monster_life_+%_final_from_deadly_atlas"
    ],
    "trade_stats": null,
    "hidden": null,
    "French": null,
    "German": null,
    "Japanese": null,
    "Korean": null,
    "Portuguese": null,
    "Russian": [
      {
        "condition": [
          {
            "min": 1,
            "max": null,
            "negated": null
          }
        ],
        "format": [
          "#"
        ],
        "index_handlers": [
          []
        ],
        "string": "Монстры на ваших картах имеют на {0}% больше здоровья",
        "reminder_text": null,
        "is_markup": null
      },
      {
        "condition": [
          {
            "min": null,
            "max": -1,
            "negated": null
          }
        ],
        "format": [
          "#"
        ],
        "index_handlers": [
          [
            "negate"
          ]
        ],
        "string": "Монстры на ваших картах имеют на {0}% меньше здоровья",
        "reminder_text": null,
        "is_markup": null
      }
    ],
    "Spanish": null,
    "Thai": null,
    "Traditional_Chinese": null
  },
  {
    "English": null,
    "ids": [
      "map_monster_life_+%_final_from_vital_atlas"
    ],
    "trade_stats": null,
    "hidden": null,
    "French": null,
    "German": null,
    "Japanese": null,
    "Korean": null,
    "Portuguese": null,
    "Russian": [
      {
        "condition": [
          {
            "min": 1,
            "max": null,
            "negated": null
          }
        ],
        "format": [
          "#"
        ],
        "index_handlers": [
          []
        ],
        "string": "Монстры на ваших картах имеют на {0}% больше здоровья",
        "reminder_text": null,
        "is_markup": null
      },
      {
        "condition": [
          {
            "min": null,
            "max": -1,
            "negated": null
          }
        ],
        "format": [
          "#"
        ],
        "index_handlers": [
          [
            "negate"
          ]
        ],
        "string": "Монстры на ваших картах имеют на {0}% меньше здоровья",
        "reminder_text": null,
        "is_markup": null
      }
    ],
    "Spanish": null,
    "Thai": null,
    "Traditional_Chinese": null
  }
]